pogmake/__init__.py
pogmake/__main__.py
pogmake/app.py
pogmake/core.py
pogmake/importer.py
pogmake/setup.py
pogmake-0.0.1.dist-info/METADATA
pogmake-0.0.1.dist-info/WHEEL
pogmake-0.0.1.dist-info/entry_points.txt
pogmake-0.0.1.dist-info/top_level.txt
pogmake-0.0.1.dist-info/RECORD
