Metadata-Version: 2.1
Name: pogmake
Version: 0.0.1
Summary: I needed a cross platform makefile
Home-page: https://github.com/peterino/pmake
Author: Peter Li
Author-email: peterlimail47@gmail.com
License: UNKNOWN
Platform: UNKNOWN
Classifier: Programming Language :: Python :: 3
Classifier: License :: OSI Approved :: MIT License
Classifier: Operating System :: OS Independent
Requires-Python: >=3.6
